textgradient/__init__.py
textgradient/config.json
textgradient/gradient.py
textgradient-0.3.dist-info/METADATA
textgradient-0.3.dist-info/WHEEL
textgradient-0.3.dist-info/entry_points.txt
textgradient-0.3.dist-info/top_level.txt
textgradient-0.3.dist-info/RECORD
