Metadata-Version: 2.1
Name: textgradient
Version: 0.3
Summary: A Python package to create gradient-colored text
Home-page: https://github.com/l/textgradient
Author: Prime
Author-email: push9352@gmail.com
Classifier: Programming Language :: Python :: 3
Classifier: License :: OSI Approved :: MIT License
Classifier: Operating System :: OS Independent
Requires-Dist: colorama
Requires-Dist: requests
